odoo/addons/partner_delivery_zone/README.rst
odoo/addons/partner_delivery_zone/__init__.py
odoo/addons/partner_delivery_zone/__manifest__.py
odoo/addons/partner_delivery_zone/i18n/de.po
odoo/addons/partner_delivery_zone/i18n/es.po
odoo/addons/partner_delivery_zone/i18n/fr_FR.po
odoo/addons/partner_delivery_zone/i18n/it.po
odoo/addons/partner_delivery_zone/i18n/partner_delivery_zone.pot
odoo/addons/partner_delivery_zone/i18n/zh_CN.po
odoo/addons/partner_delivery_zone/models/__init__.py
odoo/addons/partner_delivery_zone/models/partner_delivery_zone.py
odoo/addons/partner_delivery_zone/models/res_partner.py
odoo/addons/partner_delivery_zone/models/sale_order.py
odoo/addons/partner_delivery_zone/models/stock_move.py
odoo/addons/partner_delivery_zone/models/stock_picking.py
odoo/addons/partner_delivery_zone/readme/CONFIGURATION.rst
odoo/addons/partner_delivery_zone/readme/CONTRIBUTORS.rst
odoo/addons/partner_delivery_zone/readme/DESCRIPTION.rst
odoo/addons/partner_delivery_zone/readme/ROADMAP.rst
odoo/addons/partner_delivery_zone/readme/USAGE.rst
odoo/addons/partner_delivery_zone/security/ir.model.access.csv
odoo/addons/partner_delivery_zone/static/description/icon.png
odoo/addons/partner_delivery_zone/static/description/index.html
odoo/addons/partner_delivery_zone/tests/__init__.py
odoo/addons/partner_delivery_zone/tests/test_partner_delivery_zone.py
odoo/addons/partner_delivery_zone/views/partner_delivery_zone_view.xml
odoo/addons/partner_delivery_zone/views/report_deliveryslip.xml
odoo/addons/partner_delivery_zone/views/report_shipping.xml
odoo/addons/partner_delivery_zone/views/res_partner_view.xml
odoo/addons/partner_delivery_zone/views/sale_order_view.xml
odoo/addons/partner_delivery_zone/views/stock_picking_view.xml
odoo14_addon_partner_delivery_zone-14.0.1.1.1.dist-info/METADATA
odoo14_addon_partner_delivery_zone-14.0.1.1.1.dist-info/WHEEL
odoo14_addon_partner_delivery_zone-14.0.1.1.1.dist-info/top_level.txt
odoo14_addon_partner_delivery_zone-14.0.1.1.1.dist-info/RECORD
