Metadata-Version: 2.1
Name: odoo14-addon-partner-delivery-zone
Version: 14.0.1.1.1
Summary: Set on partners a zone for delivery goods
Home-page: https://github.com/OCA/delivery-carrier
Author: Tecnativa, Pesol, Odoo Community Association (OCA)
Author-email: support@odoo-community.org
License: AGPL-3
Platform: UNKNOWN
Classifier: Programming Language :: Python
Classifier: Framework :: Odoo
Classifier: Framework :: Odoo :: 14.0
Classifier: License :: OSI Approved :: GNU Affero General Public License v3
Classifier: Development Status :: 4 - Beta
Requires-Python: >=3.6
Requires-Dist: odoo <14.1dev,>=14.0a
